posql/__init__.py
posql/mysql.py
posql-0.1.2a0.dist-info/LICENSE
posql-0.1.2a0.dist-info/METADATA
posql-0.1.2a0.dist-info/WHEEL
posql-0.1.2a0.dist-info/top_level.txt
posql-0.1.2a0.dist-info/RECORD
