Metadata-Version: 2.1
Name: posql
Version: 0.1.2a0
Summary: A small database operation package
Home-page: UNKNOWN
Author: YinYang
Author-email: 01@yinyang.live
License: UNKNOWN
Platform: UNKNOWN
Classifier: Programming Language :: Python :: 3
Classifier: License :: OSI Approved :: MIT License
Classifier: Operating System :: OS Independent
Requires-Python: >=3.6
